odoo/addons/fs_product_multi_media/README.rst
odoo/addons/fs_product_multi_media/__init__.py
odoo/addons/fs_product_multi_media/__manifest__.py
odoo/addons/fs_product_multi_media/i18n/es.po
odoo/addons/fs_product_multi_media/i18n/fs_product_multi_media.pot
odoo/addons/fs_product_multi_media/i18n/it.po
odoo/addons/fs_product_multi_media/models/__init__.py
odoo/addons/fs_product_multi_media/models/fs_product_category_media.py
odoo/addons/fs_product_multi_media/models/fs_product_media.py
odoo/addons/fs_product_multi_media/models/product_category.py
odoo/addons/fs_product_multi_media/models/product_product.py
odoo/addons/fs_product_multi_media/models/product_template.py
odoo/addons/fs_product_multi_media/models/product_template_attribute_line.py
odoo/addons/fs_product_multi_media/readme/CONTRIBUTORS.md
odoo/addons/fs_product_multi_media/readme/DESCRIPTION.md
odoo/addons/fs_product_multi_media/readme/HISTORY.md
odoo/addons/fs_product_multi_media/readme/USAGE.md
odoo/addons/fs_product_multi_media/readme/newsfragments/.gitignore
odoo/addons/fs_product_multi_media/security/fs_product_category_media.xml
odoo/addons/fs_product_multi_media/security/fs_product_media.xml
odoo/addons/fs_product_multi_media/static/description/icon.png
odoo/addons/fs_product_multi_media/static/description/index.html
odoo/addons/fs_product_multi_media/tests/__init__.py
odoo/addons/fs_product_multi_media/tests/test_fs_product_multi_media.py
odoo/addons/fs_product_multi_media/views/fs_product_category_media.xml
odoo/addons/fs_product_multi_media/views/fs_product_media.xml
odoo/addons/fs_product_multi_media/views/product_category.xml
odoo/addons/fs_product_multi_media/views/product_product.xml
odoo/addons/fs_product_multi_media/views/product_template.xml
odoo_addon_fs_product_multi_media-17.0.1.0.0.3.dist-info/METADATA
odoo_addon_fs_product_multi_media-17.0.1.0.0.3.dist-info/WHEEL
odoo_addon_fs_product_multi_media-17.0.1.0.0.3.dist-info/top_level.txt
odoo_addon_fs_product_multi_media-17.0.1.0.0.3.dist-info/RECORD
